viznvsmi/__init__.py
viznvsmi/callback.py
viznvsmi/monitor.py
viznvsmi-0.0.1.dist-info/LICENSE
viznvsmi-0.0.1.dist-info/METADATA
viznvsmi-0.0.1.dist-info/WHEEL
viznvsmi-0.0.1.dist-info/top_level.txt
viznvsmi-0.0.1.dist-info/RECORD
