Metadata-Version: 2.1
Name: viznvsmi
Version: 0.0.1
Summary: NVSMI plugins for VizTracer
Home-page: https://github.com/clumsy/viznvsmi
Author: Alexander Jipa
Author-email: alexander.jipa@gmail.com
Classifier: Development Status :: 3 - Alpha
Classifier: Programming Language :: Python :: 3.8
Classifier: Programming Language :: Python :: 3.9
Classifier: Programming Language :: Python :: 3.10
Classifier: Programming Language :: Python :: 3.11
Classifier: Intended Audience :: Developers
Classifier: License :: OSI Approved :: Apache Software License
Classifier: Operating System :: OS Independent
Requires-Python: >=3.8
License-File: LICENSE
Requires-Dist: viztracer
Provides-Extra: lightning
Requires-Dist: pytorch-lightning; extra == "lightning"
